[
    {
        "id": "r01",
        "name": "201712-创新一-渤海-冬季-CTD",
        "startTime": "2017\/12\/23 17:10",
        "endTime": "2017\/12\/29 19:55"
    },{
        "id": "r02",
        "name": "201710-创新一-渤海-冬季-CTD",
        "startTime": "2017\/12\/23 17:10",
        "endTime": "2017\/12\/29 19:55"
    },{
        "id": "r03",
        "name": "201708-创新一-渤海-夏季-CTD",
        "startTime": "2017\/12\/23 17:10",
        "endTime": "2017\/12\/29 19:55"
    },{
        "id": "r04",
        "name": "201702-创新一-渤海-冬季-CTD",
        "startTime": "2017\/12\/23 17:10",
        "endTime": "2017\/12\/29 19:55"
    },{
        "id": "r05",
        "name": "201612-创新一-渤海-冬季-CTD",
        "startTime": "2017\/12\/23 17:10",
        "endTime": "2017\/12\/29 19:55"
    },{
        "id": "r06",
        "name": "2015年北斗轮夏季黄海航次",
        "startTime": "2017\/12\/23 17:10",
        "endTime": "2017\/12\/29 19:55"
    }
]